{
	"info": {
		"_postman_id": "c08eae57-4b88-4a0b-91d9-1aac7e833575",
		"name": "Laravel Blog API",
		"schema": "https://schema.getpostman.com/json/collection/v2.1.0/collection.json"
	},
	"item": [
		{
			"name": "Get All Posts",
			"protocolProfileBehavior": {
				"disableBodyPruning": true
			},
			"request": {
				"method": "GET",
				"header": [
					{
						"key": "Accept",
						"value": "application/json",
						"type": "text"
					}
				],
				"body": {
					"mode": "raw",
					"raw": "",
					"options": {
						"raw": {
							"language": "json"
						}
					}
				},
				"url": {
					"raw": "http://127.0.0.1:8000/api/posts",
					"protocol": "http",
					"host": [
						"127",
						"0",
						"0",
						"1"
					],
					"port": "8000",
					"path": [
						"api",
						"posts"
					]
				}
			},
			"response": []
		},
		{
			"name": "Create Post",
			"request": {
				"method": "POST",
				"header": [
					{
						"key": "Accept",
						"value": "application/json"
					}
				],
				"body": {
					"mode": "raw",
					"raw": "{\n        \"title\": \"This is fourth title\",\n        \"slug\": \"12cvc22n-\",\n        \"body\": \"This is the body.\",\n        \"is_published\": 1,\n        \"publish_date\": null,\n        \"meta_description\": \"laravel,api,backend,sql , laravel,php,validation,api,html\",\n        \"tags\": \"laravel,api,backend,sql\",\n        \"keywords\": \"laravel,php,validation,api\"\n}",
					"options": {
						"raw": {
							"language": "json"
						}
					}
				},
				"url": {
					"raw": "http://127.0.0.1:8000/api/posts",
					"protocol": "http",
					"host": [
						"127",
						"0",
						"0",
						"1"
					],
					"port": "8000",
					"path": [
						"api",
						"posts"
					]
				}
			},
			"response": []
		},
		{
			"name": "Get Post by ID",
			"protocolProfileBehavior": {
				"disableBodyPruning": true
			},
			"request": {
				"method": "GET",
				"header": [
					{
						"key": "Accept",
						"value": "application/json",
						"type": "text"
					}
				],
				"body": {
					"mode": "raw",
					"raw": "",
					"options": {
						"raw": {
							"language": "json"
						}
					}
				},
				"url": {
					"raw": "http://127.0.0.1:8000/api/posts/1",
					"protocol": "http",
					"host": [
						"127",
						"0",
						"0",
						"1"
					],
					"port": "8000",
					"path": [
						"api",
						"posts",
						"1"
					]
				}
			},
			"response": []
		},
		{
			"name": "Update Post",
			"request": {
				"method": "PUT",
				"header": [
					{
						"key": "Accept",
						"value": "application/json"
					}
				],
				"body": {
					"mode": "raw",
					"raw": "{\n  \"title\": \"Updated Post Title\",\n  \"body\": \"Updated body.\",\n  \"slug\":\"slug12x3--\",\n  \"is_published\": false,\n  \"publish_date\": \"1978-05-08\",\n  \"tags\": \"updated,post\",\n  \"keywords\": \"edit,laravel,backend,laravel,backend\"\n}",
					"options": {
						"raw": {
							"language": "json"
						}
					}
				},
				"url": {
					"raw": "http://127.0.0.1:8000/api/posts/6",
					"protocol": "http",
					"host": [
						"127",
						"0",
						"0",
						"1"
					],
					"port": "8000",
					"path": [
						"api",
						"posts",
						"6"
					]
				}
			},
			"response": []
		},
		{
			"name": "Delete Post",
			"request": {
				"method": "DELETE",
				"header": [
					{
						"key": "Accept",
						"value": "application/json",
						"type": "text"
					}
				],
				"body": {
					"mode": "raw",
					"raw": "",
					"options": {
						"raw": {
							"language": "json"
						}
					}
				},
				"url": {
					"raw": "http://127.0.0.1:8000/api/posts/7",
					"protocol": "http",
					"host": [
						"127",
						"0",
						"0",
						"1"
					],
					"port": "8000",
					"path": [
						"api",
						"posts",
						"7"
					]
				}
			},
			"response": []
		}
	]
}